MANIFEST.in
README.rst
setup.py
leboncrevard/__init__.py
leboncrevard/config.py
leboncrevard/job.py
leboncrevard/scheduler.py
leboncrevard/scrapper.py
leboncrevard.egg-info/PKG-INFO
leboncrevard.egg-info/SOURCES.txt
leboncrevard.egg-info/dependency_links.txt
leboncrevard.egg-info/entry_points.txt
leboncrevard.egg-info/not-zip-safe
leboncrevard.egg-info/requires.txt
leboncrevard.egg-info/top_level.txt