Metadata-Version: 1.1
Name: leboncrevard
Version: 0.1.1
Summary: Python scrapper / mailer for the french ad website leboncoin.fr
Home-page: https://github.com/mclbn/leboncrevard
Author: Marc Lebrun
Author-email: UNKNOWN
License: ISC
Keywords: leboncoin scrapper
Platform: UNKNOWN
Classifier: Development Status :: 3 - Alpha
Classifier: License :: OSI Approved :: ISC License (ISCL)
Classifier: Programming Language :: Python :: 3
Classifier: Programming Language :: Python :: 3.4
Classifier: Programming Language :: Python :: 3.5
Classifier: Programming Language :: Python :: 3.6
Classifier: Topic :: Text Processing :: Markup :: HTML
